dxl2/__init__.py
dxl2/connection.py
dxl2/motor.py
dxl2/motor_chain.py
dxl2/register.py
dxl2/util.py
dxl2-0.1.dist-info/LICENSE
dxl2-0.1.dist-info/METADATA
dxl2-0.1.dist-info/WHEEL
dxl2-0.1.dist-info/top_level.txt
dxl2-0.1.dist-info/RECORD
